[
    {
        "filename": "sn-sgv-9",
        "bookId": 16,
        "language": "pali",
        "entries": [
            {
                "type": "page-break",
                "text": "352"
            },
            {
                "type": "heading",
                "text": "9. වනසංයුත්තං",
                "level": 3
            },
            {
                "type": "heading",
                "text": "1. වනවග්ගො",
                "level": 2
            },
            {
                "type": "centered",
                "text": "9. 1. 1.",
                "level": "1"
            },
            {
                "type": "heading",
                "text": "විවෙකසුත්තං",
                "level": "1"
            },
            {
                "type": "paragraph",
                "text": "221. එවං මෙ සුතං: එකං සමයං අඤ්ඤතරො භික්ඛු කොසලෙසු විහරති අඤ්ඤතරස්මිං වනසණ්ඩෙ. තෙන ඛො පන සමයෙන සො භික්ඛු දිවාවිහාරගතො පාපකෙ අකුසලෙ විතක්කෙ විතක්කෙති ගෙහනිස්සිතෙ."
            },
            {
                "type": "paragraph",
                "text": "අථ ඛො යා තස්මිං වනසණ්ඩෙ අධිවත්ථා දෙවතා තස්ස භික්ඛුනො අනුකම්පිකා අත්ථකාමා තං භික්ඛුං සංවෙජෙතුකාමා යෙන සො භික්ඛු තෙනුපසඞ්කමි. උපසඞ්කමිත්වා තං භික්ඛුං ගාථාහි අජ්ඣභාසි:"
            },
            {
                "type": "gatha",
                "text": "විවෙකකාමොසි වනං පවිට්ඨො අථ තෙ මනො නිච්ඡරතී බහිද්ධා,\nජනො{1 ත්වං ජනො - ස්යා.} ජනස්මිං විනයස්සු ඡන්දං තතො සුඛී හොහිසි වීතරාගො."
            },
            {
                "type": "gatha",
                "text": "අරතිං පජහාසි සතො{2 සො සතො - PTS.} භවාසි සතං තං සාදයාමසෙ{3 සාරයාමසෙ - මඡසං. ස්යා. PTS. සී. 1, 2.},\nපාතාලරජො හි දුත්තරො{4 දුරුත්තමො - PTS.} මා තං කාමරජො අවාහරි."
            },
            {
                "type": "gatha",
                "text": "සකුණො යථා පංසුකුණ්ඩිතො{5 පංසුකුත්ථිතො - මඡසං.} විධුතං{6 විධූනං - PTS.} පාතයති සිතං රජං,\nඑවං භික්ඛු පධානවා සතිමා විධුනං පාතයති සිතං රජන්ති."
            },
            {
                "type": "paragraph",
                "text": "අථ ඛො සො භික්ඛු තාය දෙවතාය සංවෙජිතො සංවෙගමාපාදීති."
            },
            {
                "type": "centered",
                "text": "9. 1. 2.",
                "level": "1"
            },
            {
                "type": "heading",
                "text": "උපට්ඨානසුත්තං",
                "level": "1"
            },
            {
                "type": "paragraph",
                "text": "222. එකං සමයං අඤ්ඤතරො භික්ඛු කොසලෙසු විහරති අඤ්ඤතරස්මිං වනසණ්ඩෙ. තෙන ඛො පන සමයෙන සො භික්ඛු දිවාවිහාරගතො සුපති. අථ ඛො යා තස්මිං වනසණ්ඩෙ අධිවත්ථා දෙවතා තස්ස භික්ඛුනො අනුකම්පිකා අත්ථකාමා තං භික්ඛුං සංවෙජෙතුකාමා යෙන සො භික්ඛු තෙනුපසඞ්කමි."
            },
            {
                "type": "page-break",
                "text": "354"
            },
            {
                "type": "paragraph",
                "text": "උපසඞ්කමිත්වා තං භික්ඛුං ගාථාහි අජ්ඣභාසි:"
            },
            {
                "type": "gatha",
                "text": "උට්ඨෙහි භික්ඛු කිං සෙසි{1 සොපි - ස්යා.} කො අත්ථො සුපිනෙන{2 සුපිතෙන - PTS.} තෙ,\nආතුරස්ස හි කා{3 තෙ - සීමු. ස්යා.} නිද්දා සල්ලවිද්ධස්ස රුප්පතො."
            },
            {
                "type": "gatha",
                "text": "යාය සද්ධා{4 සද්ධාය - මඡසං. PTS.} පබ්බජිතො අගාරස්මානගාරියං,\nතමෙව සද්ධං බ්රෑහෙහි මා නිද්දාය වසඞ්ගමීති."
            },
            {
                "type": "gatha",
                "text": "අනිච්චා අද්ධුවා කාමා යෙසු මන්දො’ව මුච්ඡිතො,\nඛන්ධෙසු{5 බන්ධෙසු - මඡසං. ස්යා. PTS.} මුත්තං අසිතං කස්මා පබ්බජිතං තපෙ."
            },
            {
                "type": "gatha",
                "text": "ඡන්දරාගස්ස විනයා අවිජ්ජාසමතික්කමා,\nතඤ්ඤාණං පරමවොදානං{6 පරමොදානං - මඡසං. ස්යා. පරියොදාතං - PTS. සී 2.} කස්මා පබ්බජිතං තපෙ."
            },
            {
                "type": "gatha",
                "text": "භෙත්වා{7 ජෙත්වා - මඡසං.} අවිජ්ජං විජ්ජාය ආසවානං පරික්ඛයා,\nඅසොකං අනුපායාසං කස්මා පබ්බජිතං තපෙ."
            },
            {
                "type": "gatha",
                "text": "ආරද්ධවිරියං පහිතත්තං නිච්චං දළ්හපරක්කමං,\nනිබ්බාණං අභිකඞ්ඛන්තං කස්මා පබ්බජිතං තපෙති."
            },
            {
                "type": "centered",
                "text": "9. 1. 3.",
                "level": "1"
            },
            {
                "type": "heading",
                "text": "කස්සපගොත්තසුත්තං.",
                "level": "1"
            },
            {
                "type": "paragraph",
                "text": "223. එකං සමයං ආයස්මා කස්සපගොත්තො කොසලෙසු විහරති අඤ්ඤතරස්මිං වනසණ්ඩෙ. තෙන ඛො පන සමයෙන ආයස්මා කස්සපගොත්තො දිවාවිහාරගතො අඤ්ඤතරං වෙතං{8 සුණොති - PTS.} ඔවදති."
            },
            {
                "type": "paragraph",
                "text": "අථ ඛො යා තස්මිං වනසණ්ඩෙ අධිවත්ථා දෙවතා ආයස්මතො කස්සපගොත්තස්ස අනුකම්පිකා අත්ථකාමා ආයස්මං කස්සපගොත්තං සංවෙජෙතුකාමා යෙනායස්මා කස්සපගොත්තො තෙනුපසඞ්කමි. උපසඞ්කමිත්වා ආයස්මන්තං කස්සපගොත්තං ගාථාහි අජ්ඣභාසි:"
            },
            {
                "type": "gatha",
                "text": "ගිරිදුග්ගචරං චෙතං අප්පපඤ්ඤං අචෙතසං,\nඅකාලෙ ඔවදං භික්ඛු මන්දො’ව පටිභාති මං."
            },
            {
                "type": "gatha",
                "text": "සුණාති{9 ඡෙතං - ස්යා. PTS. මඡසං.} න විජානාති ආලොකෙති න පස්සති,\nධම්මස්මිං භඤ්ඤමානස්මිං අත්ථං බාලො න බුජ්ඣති."
            },
            {
                "type": "gatha",
                "text": "සචෙපි දස පජ්ජොතෙ ධාරයිස්සසි කස්සප,\nනෙව දක්ඛිති{10 දක්ඛති - සීමු.} රූපානි චක්ඛු හි’ස්ස න විජ්ජතීති."
            },
            {
                "type": "paragraph",
                "text": "අථ ඛො ආයස්මා කස්සපගොත්තො තාය දෙවතාය සංවෙජිතො සංවෙගමාපාදීති."
            },
            {
                "type": "page-break",
                "text": "356"
            },
            {
                "type": "centered",
                "text": "9. 1. 4.",
                "level": "1"
            },
            {
                "type": "heading",
                "text": "සම්බහුලාසුත්තං.",
                "level": "1"
            },
            {
                "type": "paragraph",
                "text": "224. එකං සමයං සම්බහුලා භික්ඛූ කොසලෙසු විහරන්ති අඤ්ඤතරස්මිං වනසණ්ඩෙ. අථ ඛො තෙ භික්ඛූ වස්සං වුත්ථා{1 වුට්ඨා - මඡසං.} තෙමාසච්චයෙන චාරිකං පක්කමිංසු. අථ ඛො යා තස්මිං වනසණ්ඩෙ අධිවත්ථා දෙවතා තෙ භික්ඛූ අපස්සන්තී පරිදෙවමානා තායං වෙලායං ඉමං ගාථං අභාසි:"
            },
            {
                "type": "gatha",
                "text": "අරති විය මෙ’ජ්ජ{2 මෙජ්ජං - ස්යා.} ඛායති බහුකෙ දිස්වාන විවිත්තෙ ආසනෙ,\nතෙ චිත්තකථා බහුස්සුතා කො’මෙ ගොතමසාවකා ගතාති."
            },
            {
                "type": "gatha",
                "text": "එවං වුත්තෙ අඤ්ඤතරා දෙවතා තං දෙවතං ගාථාය අජ්ඣභාසි:"
            },
            {
                "type": "gatha",
                "text": "මගධං ගතා කොසලං ගතා එකච්චියා පන වජ්ජිභූමියා,\nමගා{3 මිගා - සීමු. මක්කටා - ස්යා.} විය අසඞ්ගචාරිනො අනිකෙතා විහරන්ති භික්ඛවොති."
            },
            {
                "type": "centered",
                "text": "9. 1. 5.",
                "level": "1"
            },
            {
                "type": "heading",
                "text": "ආනන්දසුත්තං.",
                "level": "1"
            },
            {
                "type": "paragraph",
                "text": "225. එකං සමයං ආයස්මා ආනන්දො කොසලෙසු විහරති අඤ්ඤතරස්මිං වනසණ්ඩෙ.\nතෙන ඛො පන සමයෙන ආයස්මා ආනන්දො අතිවෙලං ගිහීසඤ්ඤත්තිබහුලො විහරති.\n\nඅථ ඛො යා තස්මිං වනසණ්ඩෙ අධිවත්ථා දෙවතා ආයස්මතො ආනන්දස්ස අනුකම්පිකා අත්ථකාමා ආයස්මන්තං ආනන්දං සංවෙජෙතුකාමා යෙනායස්මා ආනන්දො තෙනුපසඞ්කමි. උපසඞ්කමිත්වා ආයස්මන්තං ආනන්දං ගාථාය අජ්ඣභාසි:"
            },
            {
                "type": "gatha",
                "text": "රුක්ඛමූලගහණං පසක්කිය නිබ්බාණං හදයස්මිං ඔපිය,\nඣාය{4 ඣායී - සීමු.} ගොතම මා ච{5 මා - මඡසං. ස්යා.} පමාදො කිං තෙ බිළිබිළිකා කරිස්සතීති."
            },
            {
                "type": "paragraph",
                "text": "අථ ඛො ආයස්මා ආනන්දො තාය දෙවතාය සංවෙජිතො සංවෙගමාපාදීති."
            },
            {
                "type": "centered",
                "text": "9. 1. 6.",
                "level": "1"
            },
            {
                "type": "heading",
                "text": "අනුරුද්ධසුත්තං.",
                "level": "1"
            },
            {
                "type": "paragraph",
                "text": "226. එකං සමයං ආයස්මා අනුරුද්ධො කොසලෙසු විහරති අඤ්ඤතරස්මිං වනසණ්ඩෙ.\nඅථ ඛො අඤ්ඤතරා තාවතිංසකායිකා දෙවතා ජාලිනී නාම ආයස්මතො අනුරුද්ධස්ස පුරාණදුතියිකා යෙනායස්මා අනුරුද්ධො තෙනුපසඞ්කමි. උපසඞ්කමිත්වා ආයස්මන්තං අනුරුද්ධං ගාථාහි අජ්ඣභාසි:"
            },
            {
                "type": "gatha",
                "text": "තත්ථ චිත්තං පණිධෙහි යත්ථ තෙ වුසිතං පුරෙ,\nතාවතිංසෙසු දෙවෙසු සබ්බකාමසමිද්ධිසු,\nපුරක්ඛතො පරිවුතො දෙවකඤ්ඤාහි{6 දෙවගණෙහි - ස්යා.} සොභසීති."
            },
            {
                "type": "page-break",
                "text": "358"
            },
            {
                "type": "gatha",
                "text": "දුග්ගතා දෙවකඤ්ඤායො සක්කායස්මිං පතිට්ඨිතා,\nතෙ චාපි දුග්ගතා සත්තා දෙවකඤ්ඤාහි පත්ථිතාති."
            },
            {
                "type": "gatha",
                "text": "\nන තෙ සුඛං පජානන්ති යෙ න පස්සන්ති නන්දනං,\nආවාසං නරදෙවානං තිදසානං යසස්සිනන්ති."
            },
            {
                "type": "unindented",
                "text": "[අනුරුද්ධො:]"
            },
            {
                "type": "gatha",
                "text": "න ත්වං බාලෙ විජානාසි යථා අරහතං වචො,\nඅනිච්චා සබ්බෙ සඞ්ඛාරා උප්පාදවයධම්මිනො,\nඋප්පජ්ජිත්වා නිරුජ්ඣන්ති තෙසං වූපසමො සුඛො."
            },
            {
                "type": "gatha",
                "text": "නත්ථිදානි පුනාවාසො දෙවකායස්මිං{1 දෙවකායස්මි - මඡසං. ස්යා.} ජාලිනී,\nවික්ඛීණො ජාතිසංසාරො නත්ථිදානි පුනබ්භවොති."
            },
            {
                "type": "centered",
                "text": "9. 1. 7.",
                "level": "1"
            },
            {
                "type": "heading",
                "text": "නාගදත්තසුත්තං.",
                "level": "1"
            },
            {
                "type": "paragraph",
                "text": "227. එකං සමයං ආයස්මා නාගදත්තො කොසලෙසු විහරති අඤ්ඤතරස්මිං වනසණ්ඩෙ. තෙන ඛො පන සමයෙන ආයස්මා නාගදත්තො අතිකාලෙන ගාමං පවිසති, අතිදිවා පටික්කමති. අථ ඛො යා තස්මිං වනසණ්ඩෙ අධිවත්ථා දෙවතා ආයස්මතො නාගදත්තස්ස අනුකම්පිකා අත්ථකාමා ආයස්මන්තං නාගදත්තං සංවෙජෙතුකාමා යෙනායස්මා නාගදත්තො තෙනුපසඞ්කමි. උපසඞ්කමිත්වා ආයස්මන්තං නාගදත්තං ගාථාහි අජ්ඣභාසි:"
            },
            {
                "type": "gatha",
                "text": "කාලෙ පවිස්ස{2 පවිස - මඡසං.} නාගදත්ත දිවා ච ආගන්ත්වා අතිවෙලචාරී,\nසංසට්ඨො ගහට්ඨෙහි සමානසුඛදුක්ඛො."
            },
            {
                "type": "gatha",
                "text": "භායාමි නාගදත්තං සුප්පගබ්භං කුලෙසු විනිබද්ධං,{3 විනිබන්ධං - PTS.}\nමා හෙව මච්චුරඤ්ඤො බලවතො අන්තකස්ස වසමෙසීති.{4 වසං උපෙසීති - මඡසං.}"
            },
            {
                "type": "paragraph",
                "text": "අථ ඛො ආයස්මා නාගදත්තො තාය දෙවතාය සංවෙජිතො සංවෙගමාපාදීති."
            },
            {
                "type": "centered",
                "text": "9. 1. 8.",
                "level": "1"
            },
            {
                "type": "heading",
                "text": "කුලඝරණීසුත්තං.",
                "level": "1"
            },
            {
                "type": "paragraph",
                "text": "228. එකං සමයං අඤ්ඤතරො භික්ඛු කොසලෙසු විහරති අඤ්ඤතරස්මිං වනසණ්ඩෙ. තෙන ඛො පන සමයෙන සො භික්ඛු අඤ්ඤතරස්මිං කුලෙ අතිවෙලං අජ්ඣොගාළ්හප්පත්තො විහරති."
            },
            {
                "type": "paragraph",
                "text": "අථ ඛො යා තස්මිං වනසණ්ඩෙ අධිවත්ථා දෙවතා තස්ස භික්ඛුනො අනුකම්පිකා අත්ථකාමා තං භික්ඛුං සංවෙජෙතුකාමා යා තස්මිං කුලෙ කුලඝරණී තස්සා වණ්ණං අභිනිම්මිනිත්වා යෙන සො භික්ඛු තෙනුපසඞ්කමි. උපසඞ්කමිත්වා තං භික්ඛුං ගාථාහි අජ්ඣභාසි:"
            },
            {
                "type": "gatha",
                "text": "නදීතීරෙසු සණ්ඨානෙ සභාසු රථියාසු ච,\nජනා සඞ්ගම්ම මන්තෙන්ති මඤ්ච තඤ්ච කිමන්තරන්ති."
            },
            {
                "type": "page-break",
                "text": "360"
            },
            {
                "type": "gatha",
                "text": "බහූ හි සද්දා පච්චූහා ඛමිතබ්බා තපස්සිනා,\nන තෙන මඞ්කු හොතබ්බං න හි තෙන කිලිස්සති."
            },
            {
                "type": "gatha",
                "text": "යො ච සද්දපරිත්තාසී වනෙ වාතමිගො යථා,\nලහුචිත්තොති තං ආහු නාස්ස සම්පජ්ජතෙ වතන්ති."
            },
            {
                "type": "centered",
                "text": "9. 1. 9.",
                "level": "1"
            },
            {
                "type": "heading",
                "text": " වජ්ජිපුත්තසුත්තං",
                "level": "1"
            },
            {
                "type": "paragraph",
                "text": "229. එකං සමයං අඤ්ඤතරො වජ්ජිපුත්තකො භික්ඛු වෙසාලියං විහරති අඤ්ඤතරස්මිං වනසණ්ඩෙ. තෙන ඛො පන සමයෙන වෙසාලියං{1 වෙසාලියං වජ්ජිපුත්තකො - මඡසං.} සබ්බරත්තිවාරො{2 සබ්බරත්තිචාරො - කත්ථචි.} හොති. අථ ඛො සො භික්ඛු වෙසාලියං තූරියතාළිතවාදිතනිග්ඝොසසද්දං සුත්වා පරිදෙවමානො තායං වෙලායං ඉමං ගාථං අභාසි:"
            },
            {
                "type": "gatha",
                "text": "එකකා මයං අරඤ්ඤෙ විහරාම අපවිද්ධංව{3 අපවිට්ඨං ව - ස්යා.} වනස්මිං දාරුකං,\nඑතාදිසිකාය රත්තියා කො සු නාම අම්හෙහි{4 නාමම්හෙහි - මඡසං.} පාපියොති."
            },
            {
                "type": "paragraph",
                "text": "අථ ඛො යා තස්මිං වනසණ්ඩෙ අධිවත්ථා දෙවතා තස්ස භික්ඛුනො අනුකම්පිකා අත්ථකාමා තං භික්ඛුං සංවෙජෙතුකාමා යෙන සො භික්ඛු තෙනුපසඞ්කමි. උපසඞ්කමිත්වා තං භික්ඛුං ගාථාය අජ්ඣභාසි:"
            },
            {
                "type": "gatha",
                "text": "එකකො{5 එකකොච - ස්යා. මඡසං.} ත්වං අරඤ්ඤෙ විහරසි අපවිද්ධංව වනස්මිං දාරුකං,\nතස්ස තෙ බහුකා පිහයන්ති නෙරයිකා විය සග්ගගාමිනන්ති."
            },
            {
                "type": "paragraph",
                "text": "අථ ඛො සො භික්ඛු තාය දෙවතාය සංවෙජිතො සංවෙගමාපාදීති."
            },
            {
                "type": "centered",
                "text": "9. 1. 10.",
                "level": "1"
            },
            {
                "type": "heading",
                "text": "සජ්ඣායසුත්තං.",
                "level": "1"
            },
            {
                "type": "paragraph",
                "text": "230. එකං සමයං අඤ්ඤතරො භික්ඛු කොසලෙසු විහරති අඤ්ඤතරස්මිං වනසණ්ඩෙ. තෙන ඛො පන සමයෙන සො භික්ඛු යං සුදං පුබ්බෙ අතිවෙලං සජ්ඣායබහුලො විහරති. සො අපරෙන සමයෙන අප්පොස්සුක්කො තුණ්හීභූතො සංකසායති{6 සකමායති - ස්යා.}."
            },
            {
                "type": "paragraph",
                "text": "අථ ඛො යා තස්මිං වනසණ්ඩෙ අධිවත්ථා දෙවතා තස්ස භික්ඛුනො ධම්මං අසුණන්තී යෙන සො භික්ඛු තෙනුපසඞ්කමි. උපසඞ්කමිත්වා තං භික්ඛුං ගාථාහි අජ්ඣභාසි:"
            },
            {
                "type": "gatha",
                "text": "කස්මා තුවං ධම්මපදානි භික්ඛු නාධීයසි භික්ඛූහි සංවසන්තො,\nසුත්වාන ධම්මං ලභතිප්පසාදං දිට්ඨෙව ධම්මෙ ලභතිප්පසංසන්ති."
            },
            {
                "type": "gatha",
                "text": "අහු පුරෙ ධම්මපදෙසු ඡන්දො යාව විරාගෙන සමාගමිම්හ,\nයතො විරාගෙන සමාගමිම්හ යං කිඤ්චි දිට්ඨංව සුතං මුතං වා{7 සුතං ච මුතං - PTS.},\nඅඤ්ඤාය නික්ඛෙපනමාහු සන්තොති."
            },
            {
                "type": "page-break",
                "text": "362"
            },
            {
                "type": "centered",
                "text": "9. 1. 11.",
                "level": "1"
            },
            {
                "type": "heading",
                "text": "අයොනිසොසුත්තං.",
                "level": "1"
            },
            {
                "type": "paragraph",
                "text": "231. එකං සමයං අඤ්ඤතරො භික්ඛු කොසලෙසු විහරති අඤ්ඤතරස්මිං වනසණ්ඩෙ. තෙන ඛො පන සමයෙන සො භික්ඛු දිවාවිහාරගතො පාපකෙ අකුසලෙ විතක්කෙ විතක්කෙති, සෙය්යථිදං: කාමවිතක්කං, බ්යාපාදවිතක්කං, විහිංසාවිතක්කං."
            },
            {
                "type": "paragraph",
                "text": "අථ ඛො යා තස්මිං වනසණ්ඩෙ අධිවත්ථා දෙවතා තස්ස භික්ඛුනො අනුකම්පිකා අත්ථකාමා තං භික්ඛුං සංවෙජෙතුකාමා යෙන සො භික්ඛු තෙනුපසඞ්කමි. උපසඞ්කමිත්වා තං භික්ඛුං ගාථාහි අජ්ඣභාසි:"
            },
            {
                "type": "gatha",
                "text": "අයොනිසො මනසිකාරා සො විතක්කෙහි ඛජ්ජසි,\nඅයොනිසො{1 අයොනිං - PTS.} පටිනිස්සජ්ජ යොනිසො අනුවිචින්තය{2 අනුචින්තිය - මඡසං.}."
            },
            {
                "type": "gatha",
                "text": "සත්ථාරං ධම්මමාරබ්භ{3 ධම්මං ආරබ්භ - සීමු. ස්යා.} සඞ්ඝං සීලානි අත්තනො{4 සීලානි චත්තනො - සීමු.},\nඅධිගච්ඡසි පාමොජ්ජං පීතිසුඛමසංසයං,\nතතො පාමොජ්ජබහුලො දුක්ඛස්සන්තං කරිස්සසීති."
            },
            {
                "type": "paragraph",
                "text": "අථ ඛො සො භික්ඛු තාය දෙවතාය සංවෙජිතො සංවෙගමාපාදීති."
            },
            {
                "type": "centered",
                "text": "9. 1. 12.",
                "level": "1"
            },
            {
                "type": "heading",
                "text": "මජ්ඣන්තිකසුත්තං.",
                "level": "1"
            },
            {
                "type": "paragraph",
                "text": "232. එකං සමයං අඤ්ඤතරො භික්ඛු කොසලෙසු විහරති අඤ්ඤතරස්මිං වනසණ්ඩෙ. අථ ඛො තස්මිං වනසණ්ඩෙ අධිවත්ථා දෙවතා යෙන සො භික්ඛු තෙනුපසඞ්කමි. උපසඞ්කමිත්වා තස්ස භික්ඛුනො සන්තිකෙ ඉමං ගාථං අභාසි:"
            },
            {
                "type": "gatha",
                "text": "ඨිතෙ මජ්ඣන්හිකෙ කාලෙ සන්නිසීවෙසු{5 සන්නිසින්නෙසු - සීමු.} පක්ඛිසු,\nසණතෙව බ්රහාරඤ්ඤං{6 මහාරඤ්ඤං - සී 1, 2.} තං භයං පටිභාති මන්ති."
            },
            {
                "type": "unindented",
                "text": "[භික්ඛු:]"
            },
            {
                "type": "gatha",
                "text": "ඨිතෙ මජ්ඣන්තිකෙ කාලෙ සන්නිසීවෙසු{7 සන්නිසින්නෙසු - සීමු.} පක්ඛිසු,\nසණතෙව බ්රහාරඤ්ඤං{8 මහාරඤ්ඤං - සී 1, 2.} ‘සා රතී පටිභාති මන්ති."
            },
            {
                "type": "centered",
                "text": "9. 1. 13.",
                "level": "1"
            },
            {
                "type": "heading",
                "text": "පාකතින්ද්රියසුත්තං.",
                "level": "1"
            },
            {
                "type": "paragraph",
                "text": "233. එකං සමයං සම්බහුලා භික්ඛූ කොසලෙසු විහරන්ති අඤ්ඤතරස්මිං වනසණ්ඩෙ, උද්ධතා උන්නළා චපලා මුඛරා විකිණ්ණවාචා මුට්ඨස්සතිනො අසම්පජානා අසමාහිතා විබ්භන්තචිත්තා පාකතින්ද්රියා."
            },
            {
                "type": "paragraph",
                "text": "අථ ඛො යා තස්මිං වනසණ්ඩෙ අධිවත්ථා දෙවතා තෙසං භික්ඛූනං අනුකම්පිකා අත්ථකාමා තෙ භික්ඛූ සංවෙජෙතුකාමා යෙන තෙ භික්ඛූ තෙනුපසඞ්කමි. උපසඞ්කමිත්වා තෙ භික්ඛූ ගාථාහි අජ්ඣභාසි:"
            },
            {
                "type": "page-break",
                "text": "364"
            },
            {
                "type": "gatha",
                "text": "සුඛජීවිනො පුරෙ ආසුං භික්ඛූ ගොතමසාවකා,\nඅනිච්ඡා පිණ්ඩමෙසනා අනිච්ඡා සයනාසනං,\nලොකෙ අනිච්චතං ඤත්වා දුක්ඛස්සන්තං අකංසු තෙ."
            },
            {
                "type": "gatha",
                "text": "දුප්පොසං කත්වා අත්තානං ගාමෙ ගාමණිකා විය,\nභුත්වා භුත්වා නිපජ්ජන්ති පරාගාරෙසු මුච්ඡිතා.\nසඞ්ඝස්ස අඤ්ජලිං කත්වා ඉධෙකච්චෙ වදාමහං,\nඅපවිද්ධා{1 අපවිට්ඨා - ස්යා.} අනාථා තෙ යථා පෙතා තථෙව තෙ."
            },
            {
                "type": "gatha",
                "text": "යෙ ඛො පමත්තා විහරන්ති තෙ මෙ සන්ධාය භාසිතං,\nයෙ අප්පමත්තා විහරන්ති නමො තෙසං කරොමහන්ති."
            },
            {
                "type": "paragraph",
                "text": "අථ ඛො තෙ භික්ඛූ තාය දෙවතාය සංවෙජිතා සංවෙගමාපාදුන්ති."
            },
            {
                "type": "centered",
                "text": "9. 1. 14.",
                "level": "1"
            },
            {
                "type": "heading",
                "text": "පදුමපුප්ඵසුත්තං.",
                "level": "1"
            },
            {
                "type": "paragraph",
                "text": "234. එවං මෙ සුතං: එකං සමයං අඤ්ඤතරො භික්ඛු කොසලෙසු විහරති අඤ්ඤතරස්මිං වනසණ්ඩෙ. තෙන ඛො පන සමයෙන සො භික්ඛු පච්ඡාභත්තං පිණ්ඩපාතපටික්කන්තො පොක්ඛරණිං ඔගාහෙත්වා පදුමං උපසිඞ්ඝති."
            },
            {
                "type": "paragraph",
                "text": "අථ ඛො යා තස්මිං වනසණ්ඩෙ අධිවත්ථා දෙවතා තස්ස භික්ඛුනො අනුකම්පිකා අත්ථකාමා තං භික්ඛුං සංවෙජෙතුකාමා යෙන සො භික්ඛු තෙනුපසඞ්කමි. උපසඞ්කමිත්වා තං භික්ඛුං ගාථාය අජ්ඣභාසි:"
            },
            {
                "type": "gatha",
                "text": "යමෙතං වාරිජං පුප්ඵං අදින්නං උපසිඞ්ඝසි,\nඑකඞ්ගමෙතං ථෙය්යානං ගන්ධත්ථෙනො’සි මාරිසාති."
            },
            {
                "type": "unindented",
                "text": "[භික්ඛු:]"
            },
            {
                "type": "gatha",
                "text": "න හරාමි න භඤ්ජාමි ආරා සිඞ්ඝාමි වාරිජං,\nඅථ කෙන නු වණ්ණෙන ගන්ධත්ථෙනො’ති වුච්චති."
            },
            {
                "type": "unindented",
                "text": "[දෙවතා:]"
            },
            {
                "type": "gatha",
                "text": "ය්වායං භිසානි{2 හිංසානි - ස්යා.} ඛණති පුණ්ඩරීකානි භඤ්ජති,{3 භුඤ්ජති - PTS.}\nඑවං ආකිණ්ණකම්මන්තො කස්මා එසො න වුච්චතීති."
            },
            {
                "type": "gatha",
                "text": "ආකිණ්ණලුද්දො පුරිසො ධාතිචෙලං’ව මක්ඛිතො,\nතස්මිං මෙ වචනං නත්ථි තඤ්ච අරහාමි{4 ත්වඤ්චාරහාමි - මඡසං.} වත්තවෙ."
            },
            {
                "type": "gatha",
                "text": "අනඞ්ගණස්ස පොසස්ස නිච්චං සුචිගවෙසිනො,\nවාළග්ගමත්තං පාපස්ස අබ්භාමත්තං’ව{5 වා - PTS.} ඛායතීති."
            },
            {
                "type": "page-break",
                "text": "366"
            },
            {
                "type": "unindented",
                "text": "[භික්ඛු:]"
            },
            {
                "type": "gatha",
                "text": "අද්ධා මං යක්ඛ ජානාසි අථො මං{1 මෙ - මඡසං.} අනුකම්පසි,\nපුනපි යක්ඛ වජ්ජාසි යදා පස්සසි එදිසන්ති.{2 එදිසං - සීමු. PTS.}"
            },
            {
                "type": "unindented",
                "text": "[දෙවතා:]"
            },
            {
                "type": "gatha",
                "text": "නෙව තං උපජීවාම{3 උපජීවාමි - සීමු. PTS.} න පි තෙ භතකාම්හසෙ{4 භතකම්භසෙ - සීමු. භද්දකම්භසෙ - PTS.},\nත්වමෙව භික්ඛු ජානෙය්ය යෙන ගච්ඡෙය්ය සුග්ගතින්ති."
            },
            {
                "type": "paragraph",
                "text": "අථ ඛො සො භික්ඛු තාය දෙවතාය සංවෙජිතො සංවෙගමාපාදීති."
            },
            {
                "type": "centered",
                "text": "වනවග්ගො පඨමො.",
                "level": "1"
            },
            {
                "type": "unindented",
                "text": "**තත්රැද්දානං:**"
            },
            {
                "type": "gatha",
                "text": "විවෙකං{5 විවෙකඋපට්ඨානඤ්ච - PTS. ස්යා.} උපට්ඨානඤ්ච කස්සපගොත්තෙන{6 ගොත්තෙන ච - PTS.} සම්බහුලා\nආනන්දො අනුරුද්ධඤ්ච නාගදත්තඤ්ච කුලඝරණී\nවජ්ජිපුත්තො ච{7 ච ඉති නත්ථි - PTS.} වෙසාලී සජ්ඣායෙන{8 සජ්ඣායෙන ච - PTS.} අයොනිසො\nමජ්ඣන්තිකාලම්හි පාකතින්ද්රියා පදුමපුප්ඵෙන චුද්දස භවෙති."
            },
            {
                "type": "centered",
                "text": "වනසංයුත්තං සමත්තං.",
                "level": "1"
            },
            {
                "type": "page-break",
                "text": "end"
            }
        ],
        "pages": {
            "352": {
                "pageNum": 352,
                "footnotesCount": 6
            },
            "354": {
                "pageNum": 354,
                "footnotesCount": 10
            },
            "356": {
                "pageNum": 356,
                "footnotesCount": 6
            },
            "358": {
                "pageNum": 358,
                "footnotesCount": 4
            },
            "360": {
                "pageNum": 360,
                "footnotesCount": 7
            },
            "362": {
                "pageNum": 362,
                "footnotesCount": 8
            },
            "364": {
                "pageNum": 364,
                "footnotesCount": 5
            },
            "366": {
                "pageNum": 366,
                "footnotesCount": 8
            }
        }
    },
    {
        "language": "sinh",
        "entries": [
            {
                "type": "page-break",
                "text": "353"
            },
            {
                "type": "heading",
                "text": "9. වන සංයුත්තය\n",
                "level": 3
            },
            {
                "type": "heading",
                "text": "1. වන වර්ගය",
                "level": 2
            },
            {
                "type": "centered",
                "text": "9. 9. 1.",
                "level": "1"
            },
            {
                "type": "heading",
                "text": "විවෙක සූත්‍රය",
                "level": "1"
            },
            {
                "format": 13,
                "text": "221. මා විසින් මෙසේ අසන ලදී: එක්කලෙක එක්තරා මහණෙක් කොසොල් දනව්වෙහි එක්තරා වනලැහැබෙක වෙසෙයි. එකල්හි ඒ මහණ තෙමේ පස්කම්සුව ඇසුරු කළ ලාමක අකුසල් සිතිවිලි සිතයි.",
                "type": "paragraph"
            },
            {
                "format": 13,
                "text": "ඉක්බිති ඒ වනලැහැබෙහි අධිගෘහිත වූ, ඒ මහණහට අනුකම්පා කරණ වැඩ කැමති ඒ දෙවි තෙමේ ඒ මහණහට සංවේග දනවනු කැමැත්තේ ඒ මහණහු වෙත එළඹියේ ය. එළඹ ඒ මහණහට ගාථායෙන් කී ය:",
                "type": "paragraph"
            },
            {
                "format": 13,
                "text": "විවේකය කැමති ව වනයට පිවිසියේ වෙහි ය. එහෙත් ඔබගේ සිත පිටත හැසිරෙයි. ජනයෙක් වූ ඔබ අන්‍යජනයා කෙරෙහි ඡන්දරාගය දුරු කරව. එහෙයින් පහ ව ගිය රාග ඇත්තේ සැප ඇත්තෙක් වන්නෙහි ය.",
                "type": "paragraph"
            },
            {
                "format": 13,
                "text": "අනභිරතිය දුරු කරව. සිහි ඇත්තෙක් වෙව. ඔබ සිස්හි ඇත්තෙකැ යි, නොහොත් ඒ සත්පුරුෂධර්මය යයි අදහමු. පාතලසඞ්ඛ්‍යාත කෙලෙස්රජස් තරණය කිරීමට දුෂ්කර ම ය. කාමරාගරජස් ඔබ (අපායට) නො හෙළාවා.",
                "type": "paragraph"
            },
            {
                "format": 13,
                "text": "පස් තැවරුණා වූ පක්ෂියෙක් (පියාපත්) සලමින් (ශරීරයෙහි) ඇලුන දූවිලි යම් සේ හෙළා ද, එසේ ම ප්‍රධන් වීර්යය ඇති ස්මෘතිමත් වූ මහණ තෙම (ස්වාසන්තානය) ඇසුරු කළ (කෙලෙස්) රජස් සලමින් හෙළයි.",
                "type": "paragraph"
            },
            {
                "format": 13,
                "text": "ඉක්බිති ඒ මහණ තෙමේ ඒ දේවතාවා විසින් සංවෙගයට පමුණුවන ලද්දේ සංවේගයට (ඔතප්බියට) පැමිණියේ ය.",
                "type": "paragraph"
            },
            {
                "type": "centered",
                "text": "9. 9. 2.",
                "level": "1"
            },
            {
                "type": "heading",
                "text": "උපට්ඨාන සූත්‍රය",
                "level": "1"
            },
            {
                "format": 13,
                "text": "222. එක්කලෙක එක්තරා මහණෙක් කොසොල් දනව්වෙහි එක්තරා වනලැහැබෙක චෙසෙයි. එකල්හි ඒ මහණෙ තෙමේ දිවාවිහාරයට ගියේ නිදයි. ඉක්බිති ඒ වනලැහැබෙහි අධිගෘහිත වූ ඒ මහණහට අනුකම්පා කරණ වැඩ කැමති ඒ දෙවි තෙමේ, ඒ මහණහට සංවේගදන්වනු කැමැත්තේ ඒ මහණහු වෙත එළඹියේ ය.",
                "type": "paragraph"
            },
            {
                "type": "page-break",
                "text": "355"
            },
            {
                "format": 13,
                "text": "එළඹ ඒ මහණහට ගාථායෙන් කීය.",
                "type": "paragraph"
            },
            {
                "format": 13,
                "text": "මහණ, නැගිටුව, කිම, නිදහි ද? නිදීමෙන් තොපට කිනම් වැඩෙක් ද? ක්ලේශාතුර වූ (අවිද්‍යා විෂ පෙවූ තෘෂ්ණා) ශල්‍යයෙන් විදින ලද ගැටෙන්නාවූ තොපට කරව නින්දෙක් ද?",
                "type": "paragraph"
            },
            {
                "format": 13,
                "text": "යම් ශ්‍රද්ධාවෙකින් ගිහිගෙන් නික්ම පැවිදි වූයෙහි ද, ඒ ශ්‍රද්ධාව ම වඩව. නින්දට වසඟ නො වව.",
                "type": "paragraph"
            },
            {
                "format": 13,
                "text": "නුවණ මඳ වූ පෘතග්ජන තෙමේ යම් කාමයන්හි මුසපත් වූයේ ද, ඒ කාමයෝ අනිත්‍යයහ. අධ්‍රැවයහ. ස්කන්ධයන්හි මිදුනාවූ තෘෂ්ණාදෘෂ්ටීන් අනිඃශ්‍රිත වූ පැවිද්දකු කුමක් හෙයින් (දිවාස්වප්නය තෙමේ) තවන්නේ ද,",
                "type": "paragraph"
            },
            {
                "format": 13,
                "text": "ඡන්දරාගය වැනසීමෙන් ද, අවිද්‍යාව ඉක්ම වීමෙන් ද ඒ චතුස්සත්‍යඥානය පරම පවිත්‍ර වූයේ වෙයි. (එබඳු) පැවිද්දකු කුමක් හෙයින් තවන්නේ ද,",
                "type": "paragraph"
            },
            {
                "format": 13,
                "text": "මාර්ගඥාන විද්‍යාවෙන් අවිද්‍යාව බිඳ ආස්‍රවයන් ක්ෂය කිරීමෙන් නිශ්ශෝකී වූ උපායාස රහිත වූ පැවිද්දකු කුමක් හෙයින් තවන්නේ ද,",
                "type": "paragraph"
            },
            {
                "format": 13,
                "text": "සම්පූර්ණ වීර්යය ඇති නිවන් පිණිස මෙහෙයු සිත් ඇති නිතර දැඩි පැරකුම් ඇති නිවණ පතන පැවිද්දකු කුමක් හෙයින් තවන්නේ ද.",
                "type": "paragraph"
            },
            {
                "type": "centered",
                "text": "9. 9. 3.",
                "level": "1"
            },
            {
                "type": "heading",
                "text": "කස්සපගොත්ත සූත්‍රය",
                "level": "1"
            },
            {
                "format": 13,
                "text": "223. එක්කලෙක ආයුෂ්මත් කස්සපගොත්ත ස්ථවිර තෙමේ කොසොල් දනව්වෙහි එක්තරා වනලැහැබෙක වෙසෙයි. එකල්හි ආයුෂ්මත් කස්සපගොත්ත ස්ථවිර තෙමේ එක්තරා මුවවැද්දකුට අවවාද කෙරෙයි.",
                "type": "paragraph"
            },
            {
                "format": 13,
                "text": "ඉක්බිති ඒ වනලැහැබෙහි අධිගෘහීත වූ ආයුෂ්මත් කස්සපගොත්ත තෙරුන්ට අනුකම්පා කරණ වැඩ කැමති ඒ දෙවි තෙමේ ආයුෂ්මත් කස්සපගොත්ත තෙරුන්ට සංවේග දනවනු කැමැත්තේ ආයුෂ්මත් කස්සපගොත්ත තෙරුන් වෙත එළඹියේ ය. එළඹ ආයුෂ්මත් කස්සපගොත්ත තෙරුන්ට ගාථායෙන් කී ය:",
                "type": "paragraph"
            },
            {
                "format": 13,
                "text": "පර්වත දුර්ගයෙහි හැසිරෙණ නුවණ නැති (කරුණු නොකරුණු දැනීමෙහි සමත්) සිත් නැති මුවවැද්දකුට නොකල්හි අවවාද කරණ මහණ තෙමේ අන්ධබාලයකු මෙන් මට වැටහේ.",
                "type": "paragraph"
            },
            {
                "format": 13,
                "text": "(තොපගේ බණ) අසයි. (එහෙත් අරුත්) නො දනී. (පුහුදුන් ඉදුහයෙන් දිලෙන පටඇඟිලි) බලයි. (එහි කරුණු) නො දකී. බණ කියන කල්හි අඥාන තෙමේ අරුත් අවබෝධ නො කෙරෙයි.",
                "type": "paragraph"
            },
            {
                "format": 13,
                "text": "පින්වත් කස්සප, ඉදින් ඇඟිලි පහන් දශයක් දරන්නෙහි නමුත් (හෙතු) රූපයන් නොම දක්නේ ය. යම් හෙයෙකින් ඕහට පැණැස නැද්ද (එහෙයිනි).",
                "type": "paragraph"
            },
            {
                "format": 13,
                "text": "ඉක්බිති ආයුෂ්මත් කස්සපගොත්ත ස්ථවිර තෙමේ ඒ දේවතාවා විසින් සංවේගයට (ඔතප්බියට) පමුණුවන ලද්දේ සංවිගන වී ය.",
                "type": "paragraph"
            },
            {
                "type": "page-break",
                "text": "357"
            },
            {
                "type": "centered",
                "text": "9. 9. 4.",
                "level": "1"
            },
            {
                "type": "heading",
                "text": "සම්බහුලා සූත්‍රය",
                "level": "1"
            },
            {
                "format": 13,
                "text": "224. එක්කලෙක බොහෝ භික්ෂූහු කොසොල් දනව්වෙහි එක්තරා වනලැහැබෙක වෙසෙත්. ඉක්බිති ඒ භික්ෂූහු වස් එළඹුනාහු තෙමස අවෑමෙන් චාරිකාවට ගියහ. එකල්හි ඒ වනලැහැබෙහි අධිගෘහිත වූ ඒ දෙවි තෙමේ ඒ භික්ෂූන් නො දක්නේ හඬමින් ඒ වෙලාවෙහි මේ ගාථාව කී ය:",
                "type": "paragraph"
            },
            {
                "format": 13,
                "text": "හිස් වූ බොහෝ අසුන් දැක මට අද අරතියක් මෙන් වැටෙහෙයි. විසිතුරු කථා ඇති බහුශ්‍රැත වූ ඒ මේ ගොයුම් සව්වෝ කොහි වැඩියාහු ද.",
                "type": "paragraph"
            },
            {
                "format": 13,
                "text": "මෙසේ කී කල්හි එක්තරා දෙවියෙක් දේවතාවාට මේ ගාථාව කී ය:",
                "type": "paragraph"
            },
            {
                "format": 13,
                "text": "ඇතැම් කෙනෙක් මගධ දනව්වට වැඩියහ. (ඇතැම් කෙනෙක්) කොසොල් දනව්වට වැඩියහ. (ඇතැම් කෙනෙක්) වැදෑරටට අභිමුඛ ව (වැඩියහ.) භික්ෂූහු ඇල්මක් නැති ව හැසිරෙන්නාහු ගෙයක් නැති ව මුවන් මෙන් වෙසෙත්.",
                "type": "paragraph"
            },
            {
                "type": "centered",
                "text": "9.9.5.",
                "level": "1"
            },
            {
                "type": "heading",
                "text": "ආනන්ද සූත්‍රය",
                "level": "1"
            },
            {
                "format": 13,
                "text": "225. එක්කලෙක ආයුෂ්මත් ආනන්ද ස්ථිවිර තෙමේ කොසොල් දනව්වෙහි එක්තරා වනලැහැබෙක වෙසෙයි. එකල්හි ආයුෂ්මත් ආනන්ද ස්ථිවිර තෙමේ අතිමාත්‍ර කාලයක් ගිහියන් කෙරෙහි හැඟවිලි (ඇවැත්නි නොහඬව යනාදි නැලවිලි) බහුල කොට ඇති ව වෙසෙයි. ඉක්බිති ඒ වනලැහැබෙහි අධිගෘහිත වූ අනඳ තෙරුන්ට අනුකම්පා කරණ වැඩ කැමැති දෙවි අනඳ තෙරුන් සංවිග්න කරවනු කැමැත්තේ අනඳ තෙරුන් වෙත එළඹියේ ය. එළඹ ආයුෂ්මත් අනඳ තෙරුන්ට ගාථායෙන් කී ය.",
                "type": "paragraph"
            },
            {
                "format": 13,
                "text": "රුක්මුල සෙනසුන්හි විසීමට පිවිසි නිවණ ලෙහි බහා ගෙණ (වෙසෙන) නුඹවහන්සේට (ගිහියන් සමග කරණ මේ) බිළිබිළි කථාව කුමක් කෙරේ ද? ගෞතමයන් වහන්ස, පමා නොවන මැනව. ධ්‍යාන කරණු මැනව.",
                "type": "paragraph"
            },
            {
                "format": 13,
                "text": "ඉක්බිති ආයුෂ්මත් ආනන්ද ස්ථවිර තෙමේ ඒ දේවතාවා විසින් සංවේගයට පමුණුවන ලද්දේ සංවිග්න වී ය.",
                "type": "paragraph"
            },
            {
                "type": "centered",
                "text": "9. 9. 6.",
                "level": "1"
            },
            {
                "type": "heading",
                "text": "අනුරුද්ධ සූත්‍රය",
                "level": "1"
            },
            {
                "format": 13,
                "text": "226. එක්කලෙක අනුරුද්ධ ස්ථවිර තෙමේ කොසොල් දනව්වෙහි එක්තරා වනලැහැබෙක වෙසෙයි. එකල්හි ආයුෂ්මත් අනුරුද්ධ තෙරුන්ගේ පෙරඅත්බව්හි බිරියක් වූ තව්තිසාවැසි ජාලිනී නම් එක්තරා දෙව්දුවක් ආයුෂ්මත් අනුරුද්ධ තෙරුන් වෙත එළඹියා. එළඹ ආයුෂ්මත් අනුරුද්ධ තෙරුන්ට ගාථායෙන් කිවු ය.",
                "type": "paragraph"
            },
            {
                "format": 13,
                "text": "පෙර යම් දෙව්ලොවෙක නුඹවහන්සේ විසීම වී ද, එහි සිත පිහිටුවනු මැනව. සියලු කාමයෙන් සමෘද්ධ වූ තව්තිසා දෙවියන් කෙරෙහි දෙවඟනන් විසින් පෙරටු කරණ ලදු ව, පිරිවරණ ලදු ව බැබළුනුහු,",
                "type": "paragraph"
            },
            {
                "type": "page-break",
                "text": "359"
            },
            {
                "format": 13,
                "text": "දෙවඟනෝ (ප්‍රතිපත්ති දුර්ගතියෙන්) දුර්ගතයහ. සත්කායයෙහි පිහිටියෝ ය. දෙවඟනන් විසින් පතන ලද ඒ සත්වයෝ ද දුර්ගතයහ.",
                "type": "paragraph"
            },
            {
                "type": "paragraph",
                "text": "යම් කෙනෙක් පිරිවර - යශස් ඇති තිදස්වැසි දේවපුරුෂයන්ගේ නදුනුයන නො දකිද්ද ඔහු සුවය නො දනිත්."
            },
            {
                "format": 13,
                "text": "[අනුරුද්ධ:]",
                "type": "unindented"
            },
            {
                "format": 13,
                "text": "බාලතැනැත්තිය, “සියලු සංස්කාරයෝ අනිත්‍යයහ. ඉපදීම හා නැසීම ස්වභාව කොට ඇත්තාහ. ඉපිද නිරුද්ධ වෙත්. ඔවුන්ගේ සංහිඳීම සුව ය” යන රහතුන්ගේ වදන පරිදි තෝ නො දන්නහු.",
                "type": "paragraph"
            },
            {
                "format": 13,
                "text": "එම්බා, ජාලිනි, දැන් දේවකායෙහි නැවත විසීමෙක් (මට) නැත. ඉපදීම යයි කියන ලද සංසාරය ක්ෂීණ වූයේ ය. දැන් පුනර්භවයෙක් (මට) නැත.",
                "type": "paragraph"
            },
            {
                "type": "centered",
                "text": "9.9.7.",
                "level": "1"
            },
            {
                "type": "heading",
                "text": "නාගදත්ත සූත්‍රය",
                "level": "1"
            },
            {
                "format": 13,
                "text": "227. එක්කලෙක ආයුෂ්මත් නාගදත්ත ස්ථවිර තෙමේ කොසොල් දනව්වෙහි එක්තරා වනලැහැබෙක වෙසෙයි. එකල්හි ආයුෂ්මත් නාගදත්ත ස්ථවිර තෙමේ ඉතා කලින් ගමට පිවිසෙයි. ඉතා දවල් පෙරළා එයි. ඉක්බිති ඒ වනලැහැබෙහි අධිගෘහීත වූ ආයුෂ්මත් නාගදත්ත තෙරුන්ට අනුකම්පා කරණ වැඩ කැමති ඒ දෙවි ආයුෂ්මත් නාගදත්ත තෙරුන් සංවිග්න කරවනු කැමැත්තේ ආයුෂ්මත් නාගදත්ත තෙරුන් වෙත එළඹියේ ය. එළඹ ආයුෂ්මත් නාගදත්ත තෙරුන්ට ගාථායෙන් කී ය:",
                "type": "paragraph"
            },
            {
                "format": 13,
                "text": "නාගදත්ත, අලුයම් කාලයෙහි (පිඬු පිණිස) පිවිස වෙලාව ඉක්මවා හැසිරන සුලු වූයෙහි ගිහියන් හා හැනුනෙහි ඉතා දවල් පෙරළා අවුත් (ගිහියන් හා) සමාන සුවදුක් ඇත්තෙහිය.",
                "type": "paragraph"
            },
            {
                "format": 13,
                "text": "ඉතා බුහුටි වූ කුලයන්හි බැඳුනා වූ නාගදත්ත (මහණහු ගැණ) බමි. බලවත් වූ මෘත්‍යුරාජ වූ මරුගේ වශයට නො ම පැමිණෙව.",
                "type": "paragraph"
            },
            {
                "format": 13,
                "text": "ඉක්බිති ආයුෂ්මත් නාගදත්ත ස්ථවිර තෙමේ ඒ දේවතාව විසින් සංවේගයට පමුණුවන ලද්දේ සංවිග්න වි ය.",
                "type": "paragraph"
            },
            {
                "type": "centered",
                "text": "9.9.8.",
                "level": "1"
            },
            {
                "type": "heading",
                "text": "කුලඝරණී සූත්‍රය",
                "level": "1"
            },
            {
                "format": 13,
                "text": "228. එක්කලෙක එක්තරා මහණෙක් කොසොල් දනව්වෙහි එක්තරා වනලැහැබෙක වෙසෙයි. එකල්හි ඒ මහණ තෙමේ එක්තරා කුලයක් කෙරෙහි අතිශය ඇතුළත් බවට පැමිණියේ අතිමාත්‍රකාලයක් වැඩ වෙසෙයි.",
                "type": "paragraph"
            },
            {
                "format": 13,
                "text": "ඉක්බිති ඒ වනලැහැබෙහි අධිගෘහිත වූ ඒ මහණහට අනුකම්පා කරණ වැඩ කැමති ඒ දෙවි ඒ මහණ සංවිග්න කරවනු කැමැත්තේ ඒ කුලයෙහි ඒ කුලගෙහඹු වෙස් ගෙණ ඒ මහණ වෙත එළඹියේ ය. එළඹ ඒ මහණහට ගාථායෙන් කී ය:",
                "type": "paragraph"
            },
            {
                "format": 13,
                "text": "ගං තෙර ද, විඩා සංහිඳුවන තැන ද, සභායෙහි ද, වීථියෙහි ද, ජනයෝ මුළු දී මා ගැණ ද, නුඹ වහන්සේ ගැණ ද කථා කෙරෙත්. කුමන හේතු ද?",
                "type": "paragraph"
            },
            {
                "type": "page-break",
                "text": "361"
            },
            {
                "format": 13,
                "text": "තපස්වීහු විසින් ඉවසියයුතු වූ ප්‍රතිලොමශබ්දයෝ බොහෝහ. ඒ තපස්වීහු විසින් නිතෙද නො වියයුතුයි. එයින් නො ම කිලිටි වේ.",
                "type": "paragraph"
            },
            {
                "format": 13,
                "text": "යමෙක් වෙනෙහි වාතමෘගයකු මෙන් ශබ්දයෙන් තැති ගන්නාසුලු වේ ද, ඔහු ලුහු සිත් ඇතියහ යි කියත්. ඔහුගේ ව්‍රතය නොසැපයේ.",
                "type": "paragraph"
            },
            {
                "type": "centered",
                "text": "9.9.9.",
                "level": "1"
            },
            {
                "type": "heading",
                "text": "වජ්ජිපුත්ත සූත්‍රය",
                "level": "1"
            },
            {
                "format": 13,
                "text": "229. එක්කලෙක එක්තරා වජ්ජිපුත්තක මහණෙක් විසල්පුර සමීපයෙහි එක්තරා වනලැහැබෙක වෙසෙයි. එකල්හි විසල්පුරයෙහි සව්රෑකෙළියෙක් වෙයි. ඉක්බිති ඒ මහණ තෙමේ විසල්පුරයෙහි තැළු තුරුයෙහි හා වැයු වෙණෙහි හා ගොස හා හඬ අසා හඬමින් ඒ වේලයෙහි මේගාථාව කී ය:",
                "type": "paragraph"
            },
            {
                "format": 13,
                "text": "අපි වෙනෙහි පියන ලද දරකඩක් මෙන් මෙබඳු රැයෙහි එකලාවමෝ අරණෙහි වසම්හ. කවරෙක් නම් අප වරා අතිශය පාප ඇතියෙක් වේ ද?",
                "type": "paragraph"
            },
            {
                "format": 13,
                "text": "ඉක්බිති ඒ වනලැහැබෙහි අධිගෘහිත වූ ඒ මහණහට අනුකම්පා කරණ වැඩ කැමැති ඒ දෙවි ඒ මහණහට සංවෙග දනවනු කැමැත්තේ ඒ මහණහු වෙත එළඹියේ ය. එළඹ ඒ මහණහට ගාථායෙන් කී ය:",
                "type": "paragraph"
            },
            {
                "format": 13,
                "text": "තෙපි වෙනෙහි ලූ දරකඩක් මෙන් අරණෙහි එකලා ව වසව. ඒ තොපට දෙව්ලොව යන්නවුන් ට (කැමති වන්නා වූ) නිරීසතුන් මෙන් බොහෝ දෙනෙක් කැමති වෙති.",
                "type": "paragraph"
            },
            {
                "format": 13,
                "text": "ඉක්බිති ඒ මහණ තෙමේ ඒ දේවතාවා විසින් සංවේගයට (ඔතප් බියට) පමුණුවන ලද්දේ සංවිග්න වූයේ ය.",
                "type": "paragraph"
            },
            {
                "type": "centered",
                "text": "9.9.10.",
                "level": "1"
            },
            {
                "type": "heading",
                "text": "සජ්ඣාය සූත්‍රය",
                "level": "1"
            },
            {
                "format": 13,
                "text": "230. එක්කලෙක එක්තරා මහණෙක් කොසොල් දනව්වෙහි එක්තරා වනලැහැබෙක වෙසෙයි. එකල්හි ඒ මහණ තෙමේ පෙර අතිමාත්‍රකාලයක් හැදෑරීම් බහුල කොට ඇත්තේ වෙසෙයි. (එහෙත්) හෙ තෙමේ පසුකලෙක උත්සාහ රහිත වූයේ කල් ගෙවයි.",
                "type": "paragraph"
            },
            {
                "format": 13,
                "text": "එකල්හි ඒ වනලැහැබෙහි අධිගෘහිත වූ දෙවි ඒ මහණහුගේ ධර්මය නො අසන්නේ ඒ මහණහු වෙත එළඹියේ ය. එළඹ ඒ මහණහට ගාථායෙන් කී ය.",
                "type": "paragraph"
            },
            {
                "format": 13,
                "text": "මහණ, නුඹ වහන්සේ භික්ෂූන් සමග වෙසෙමින් කුමක් හෙයින් ධර්මපදයන් නොහදාරන්නහු ද? ධර්මය අසා පැහැදීම ලබ යි. ඉහාත්මයෙහි ම පැසැසීම ද ලබයි.",
                "type": "paragraph"
            },
            {
                "format": 13,
                "text": "යම්තාක් ආර්යමාර්ගය හා එක් වූවමෝ ද, (ඊට) පෙර ධර්මපදයන්හි ඡන්දරාගය වී ය. යම් හෙයකින් ආර්යමාර්ගය හා එක් වුවමෝ ද (එහෙයින්) යම් කිසි ඇසින් දුටු රූපයෙක් හෝ කණින් ඇසූ ශබ්දයෙක් හෝ කයින් පහස්නා ලද ස්ප්‍රෂ්ටව්‍යයෙක් හෝ වේ ද, (ඒ සියල්ල අනිත්‍යාදි වශයෙන්) දැන දුර ලීම කළම්හ. ආර්යයෝ එය කියත්.",
                "type": "paragraph"
            },
            {
                "type": "page-break",
                "text": "363"
            },
            {
                "type": "centered",
                "text": "9.9.11.",
                "level": "1"
            },
            {
                "type": "heading",
                "text": "අයොනිසො සූත්‍රය",
                "level": "1"
            },
            {
                "format": 13,
                "text": "231. එක්කලෙක එක්තරා මහණෙක් කොසොල් දනව්වෙහි එක්තරා වනලැහැබෙක වෙසෙයි. එකල්හි ඒ මහණ තෙමේ දිවා විහාරයට ගියේ ලාමක අකුසල විතර්කයන් (කාමවිතර්කය, ව්‍යාපාද විතර්කය, විහිංසා විතර්කය) විතර්කනය කෙරෙයි.",
                "type": "paragraph"
            },
            {
                "format": 13,
                "text": "ඉක්බිති ඒ වනලැහැබෙහි අධිගෘහිත වූ ඒ මහණහට අනුකම්පා කරණ වැඩ කැමති ඒ දෙවි ඒ මහණහට සංවෙග දනවනු කැමැත්තේ ඒ මහණහු වෙත එළඹියේ ය. එළඹ ඒ මහණහට ගාථායෙන් කී ය:",
                "type": "paragraph"
            },
            {
                "format": 13,
                "text": "නුනුවණින් මෙනෙහි කිරීමෙන් ඒ තෙපි පාපවිතර්කයන් විසින් කනු ලැබහු. නුනුවණින් මෙනෙහි කිරීම බැහැර කොට නුවණින් මෙනෙහි කරව.",
                "type": "paragraph"
            },
            {
                "format": 13,
                "text": "ශාස්තෲන් වහන්සේ ද ධර්මය ද සඞ්ඝයා ද තමාගේ සිල් ද ඇරබ ඒකාන්තයෙන් ප්‍රමෝද්‍යයත් ප්‍රීතිය හා සුවත් ලබව. එයින් ප්‍රමෝදය බහුල කොට ඇතිව දුක් කෙළවර කරන්නාහු ය.",
                "type": "paragraph"
            },
            {
                "format": 13,
                "text": "ඉක්බිති ඒ මහණ තෙමේ ඒ දේවතාවා විසින් සංවේගයට පමුණුවන ලද්දේ සංවිග්න වූයේ ය.",
                "type": "paragraph"
            },
            {
                "type": "centered",
                "text": "9.9.12.",
                "level": "1"
            },
            {
                "type": "heading",
                "text": "මජ්ඣන්තික සූත්‍රය",
                "level": "1"
            },
            {
                "format": 13,
                "text": "232. එක්කලෙක එක්තරා මහණෙක් කොසොල් දනව්වෙහි එක්තරා වනලැහැබෙක වෙසෙයි. එකල්හි ඒ වනලැහැබෙහි අධිගෘහිත වූ ඒ දෙවි ඒ මහණ වෙත එළඹියේ ය. එළඹ ඒ මහණහුගේ සමීපයෙහි මේ ගාථාව කී ය:",
                "type": "paragraph"
            },
            {
                "format": 13,
                "text": "සිටිමද්දහනෙහි පක්ෂීන් ඉසඹු ලනකල්හි මහවනය. (මහත්සේ) හඬ නගන්නාක් මෙනි. එය මට බියක් ව වැටහේ.",
                "type": "paragraph"
            },
            {
                "format": 13,
                "text": "[භික්ෂූ:]",
                "type": "unindented"
            },
            {
                "format": 13,
                "text": "සිටිමද්දහනෙහි පක්ෂීන් ඉසඹු ලනකල්හි මහවනය මහත් සේ හඬ නගන්නාක් මෙනි. එය මට සිත් පිණවන්නාක් ව වැටහේ.",
                "type": "paragraph"
            },
            {
                "type": "centered",
                "text": "9.9.13.",
                "level": "1"
            },
            {
                "type": "heading",
                "text": "පාකතින්ද්‍රිය සූත්‍රය",
                "level": "1"
            },
            {
                "format": 13,
                "text": "233. එක්කලෙක උඩනු වූ නැඟූ මානනළ ඇති චපල වූ රළු වචන ඇති දොඩමලු වූ මුළා සිහි ඇති මනා නුවණ නැති නො එකඟ සිත් ඇති නො සන්සුන් සිත් ඇති පියවි ඉඳුරන් ඇති බොහෝ භික්ෂූහු කොසොල් දනව්වෙහි එක්තරා වනලැහැබෙක වෙසෙත්.",
                "type": "paragraph"
            },
            {
                "format": 13,
                "text": "එකල ඒ වනලැහැබ අරක් ගත ඒ භික්ෂූන්ට අනුකම්පා කරණ වැඩ කැමති ඒ දෙවි ඒ භික්ෂූන්ට සංවේග දනවනු කැමැත්තේ ඒ භික්ෂූන් වෙත එළඹියේ ය. එළඹ ඒ භික්ෂූන්ට ගාථායෙන් කී ය:",
                "type": "paragraph"
            },
            {
                "type": "page-break",
                "text": "365"
            },
            {
                "format": 13,
                "text": "පෙර ආශා රහිත ව පිඬු සොයන ආශා රහිත ව සෙනසුන් සොයන ගොයුම්සවු වූ මහණහු සුවදිවි ඇති වූහ. ඔහු ලොව අනිස් බැව් දැන දුක කෙළවර කළහ.",
                "type": "paragraph"
            },
            {
                "format": 13,
                "text": "මම සඞ්ඝයාට ඇඳිලි බැඳ කියමි. මෙහි ඇතැම්හු ගම්හි නින්දිත ගම් දෙටුවන් මෙන් තමන් දුකසේ පෝෂණය කළ හැක්කවුන් කොට අන්ගෙවල පුනපුනා බුදිමින් මුසපත් ව හොවිත්. සස්නෙන් බැහැර වූ ඔහු අසරණයෝ ය.සොහොනෙහි දමන ලද මළසිරුර බඳු වෙත්.",
                "type": "paragraph"
            },
            {
                "format": 13,
                "text": "යම් කෙනෙක් ප්‍රමත්ත ව වෙසෙත් නම් මා විසින් ඔවුන් සඳහා කියන ලදී. යම් කෙනෙක් අප්‍රමත්ත ව වෙසෙත් නම් මම ඔවුන්ට නමස්කාර කරමි.",
                "type": "paragraph"
            },
            {
                "format": 13,
                "text": "ඉක්බිති ඒ භික්ෂූහු ඒ දේවතාවා විසින් සංවේගයට පමුණුවන ලද්දාහු සංවේගයට පැමිණියහ.",
                "type": "paragraph"
            },
            {
                "type": "centered",
                "text": "9.9.14.",
                "level": "1"
            },
            {
                "type": "heading",
                "text": "පදුමපුප්ඵ සූත්‍රය",
                "level": "1"
            },
            {
                "format": 13,
                "text": "234. මා විසින් මෙසේ අසන ලදී: එක්කලෙක එක්තරා මහණෙක් කොසොල් දනව්වෙහි එක්තරා වනලැහැබෙක වැඩ වෙසෙයි. එකල්හි ඒ මහණ පසුබත පිණ්ඩපාතයෙන් වැළකුණේ පොකුණට බැස පියුමක් සිඹී.",
                "type": "paragraph"
            },
            {
                "format": 13,
                "text": "ඉක්බිති ඒ වනලැහැබ අරක්ගත් ඒ මහණහට අනුකම්පා කරණ වැඩ කැමති ඒ දෙවි ඒ මහණහට සංවේගය දනවනු කැමැත්තේ ඒ මහණහු වෙත එළඹියේ ය. එළඹ ඒ මහණහට ගාථායෙන් කී ය.",
                "type": "paragraph"
            },
            {
                "format": 13,
                "text": "නො දෙන ලද යම් ඒ පියුමක් සිඹිහි ද, මෙය සොරකම් අතුරෙන් එක් කොටසෙකි. නිදුකානන් වහන්ස, (එහෙයින්) ගන්ධත්ථෙන (සුවඳ සොරෙක්) වෙහි ය.",
                "type": "paragraph"
            },
            {
                "format": 13,
                "text": "[භික්ෂු:]",
                "type": "unindented"
            },
            {
                "format": 13,
                "text": "මේ පියුම ගෙණ නො යෙමි. නො කඩමි. දුර සිට සිඹිමි. එසේ ඇති කළ කිනම් කරුණෙකින් ගන්ධත්ථෙන යයි කියනු ලැබේ ද,",
                "type": "paragraph"
            },
            {
                "format": 13,
                "text": "[දෙවි:]",
                "type": "unindented"
            },
            {
                "format": 13,
                "text": "යම් ඒ තවුසෙක් නෙලුඹල කණී ද, පියුම් නෙළා ද, මෙසේ අපිරිසිදු කර්මාන්ත ඇති මේ තවුස් කුමක් හෙයින් ගන්ධත්ථෙන යයි නො කියනු ලැබේ ද.",
                "type": "paragraph"
            },
            {
                "format": 13,
                "text": "ඒ පුරුෂ තෙමේ බොහෝ පව් ඇත්තෙකි. කිරි මව හැඳිවත උච්චාරපස්සාවා (මලමූත්‍රා) දියෙහි ගැවසී ගත්තාක් මෙන් (රාගදොෂාදියෙන්) වැකුණෙකි. ඔහු කෙරෙහි මාගේ බසෙක් නැත. ඔබට නම් කියන්නට නිසි වෙමි.",
                "type": "paragraph"
            },
            {
                "format": 13,
                "text": "කෙලෙස් නැති නිතර පවිත්‍ර වූ ශීලාසමාධි ආදී ඥානයන් සොයන්නා වූ පුද්ගලයාට පාපය පිළිබඳ වලග පමණ වූ (ඉතා මඳ) දෝෂය පවා වලා පටලයක් පමණ වූවාක් මෙන් වැටහේ.",
                "type": "paragraph"
            },
            {
                "type": "page-break",
                "text": "367"
            },
            {
                "format": 13,
                "text": "[භික්ෂු:]",
                "type": "unindented"
            },
            {
                "format": 13,
                "text": "යක්ෂය, මා ඒකාන්තයෙන් පිරිසිදු ය යි දන්නේ හි ය. මට අනුකම්පා කෙරෙහි. යම් කලෙක මෙබන්දක් දක්නෙහි නම් යක්ෂය, නැවතත් කියන්නේහි ය.",
                "type": "paragraph"
            },
            {
                "format": 13,
                "text": "[දෙවි:]",
                "type": "unindented"
            },
            {
                "format": 13,
                "text": "මහණ, තොප නිසා නො ම ජිවත් වම්හ. තොපගේ බැළයමෝ නො ද වම්හ. යම් කර්මයෙකින් සුගතියට යන්නේ ද, (එය) තො ම දන්නෙහි ය.",
                "type": "paragraph"
            },
            {
                "format": 13,
                "text": "ඉක්බිති ඒ මහණ තෙමේ ඒ දේවතාවා විසින් සංවේගයට පමුණුවන ලද්දේ සංවේගයට පැමිණියේ ය.",
                "type": "paragraph"
            },
            {
                "format": 11,
                "text": "වනවර්ගය පළමුවැනි යි.",
                "type": "centered",
                "level": "1"
            },
            {
                "format": 20,
                "text": "**එහි උද්දානය:**",
                "type": "unindented"
            },
            {
                "format": 20,
                "text": "විවෙක, උපට්ඨාන, කස්සපගොත්ත, සම්බහුලා, ආනන්ද, අනුරුද්ධ, නාගදත්ත, කුලඝරණී, වජ්ජිපුත්ත, සඡ්ඣාය, අයොනිසො, මඡ්ඣන්තික, පාකතින්ද්‍රිය, පදුමපුප්ඵ යයි සූත්‍ර තුදුසෙකි.",
                "type": "paragraph"
            },
            {
                "format": 9,
                "text": "වනසංයුත්තය නිමියේ ය.",
                "type": "centered",
                "level": "1"
            },
            {
                "text": "end",
                "type": "page-break"
            }
        ]
    }
]